paros_data_grabber/__init__.py
paros_data_grabber/creds/influx-creds.enc
paros_data_grabber-0.1.1.dist-info/METADATA
paros_data_grabber-0.1.1.dist-info/WHEEL
paros_data_grabber-0.1.1.dist-info/top_level.txt
paros_data_grabber-0.1.1.dist-info/RECORD
